keras_rcnn/__init__.py
keras_rcnn/metrics.py
keras_rcnn/models.py
keras_rcnn/backend/__init__.py
keras_rcnn/backend/common.py
keras_rcnn/backend/tensorflow_backend.py
keras_rcnn/backend/theano_backend.py
keras_rcnn/datasets/__init__.py
keras_rcnn/datasets/malaria.py
keras_rcnn/datasets/pascal.py
keras_rcnn/layers/__init__.py
keras_rcnn/layers/pooling.py
keras_rcnn/layers/object_detection/__init__.py
keras_rcnn/layers/object_detection/_anchor.py
keras_rcnn/layers/object_detection/_object_proposal.py
keras_rcnn/layers/object_detection/_region_proposal_network.py
keras_rcnn/losses/__init__.py
keras_rcnn/losses/rcnn.py
keras_rcnn/losses/rpn.py
keras_rcnn/preprocessing/__init__.py
keras_rcnn/preprocessing/_object_detection.py
keras_rcnn-0.0.2.dist-info/DESCRIPTION.rst
keras_rcnn-0.0.2.dist-info/METADATA
keras_rcnn-0.0.2.dist-info/RECORD
keras_rcnn-0.0.2.dist-info/WHEEL
keras_rcnn-0.0.2.dist-info/metadata.json
keras_rcnn-0.0.2.dist-info/top_level.txt
tests/backend/__init__.py
tests/backend/test_common.py
tests/backend/test_tensorflow_backend.py
tests/losses/__init__.py
tests/losses/test_rcnn.py
tests/losses/test_rpn.py
