Metadata-Version: 2.0
Name: keras-rcnn
Version: 0.0.2
Summary: UNKNOWN
Home-page: https://github.com/broadinstitute/keras-rcnn
Author: Allen Goodman
Author-email: allen.goodman@icloud.com
License: MIT
Platform: UNKNOWN
Requires-Dist: keras
Provides-Extra: test
Requires-Dist: codecov; extra == 'test'
Requires-Dist: mock; extra == 'test'
Requires-Dist: pytest; extra == 'test'
Requires-Dist: pytest-cov; extra == 'test'
Requires-Dist: pytest-pep8; extra == 'test'
Requires-Dist: pytest-runner; extra == 'test'
